mj_python_social_auth-0.2.22.dist-info/METADATA
mj_python_social_auth-0.2.22.dist-info/RECORD
mj_python_social_auth-0.2.22.dist-info/WHEEL
mj_python_social_auth-0.2.22.dist-info/top_level.txt
social/__init__.py
social/actions.py
social/exceptions.py
social/p3.py
social/store.py
social/utils.py
social/apps/__init__.py
social/apps/cherrypy_app/__init__.py
social/apps/cherrypy_app/models.py
social/apps/cherrypy_app/utils.py
social/apps/cherrypy_app/views.py
social/apps/django_app/__init__.py
social/apps/django_app/context_processors.py
social/apps/django_app/middleware.py
social/apps/django_app/tests.py
social/apps/django_app/urls.py
social/apps/django_app/utils.py
social/apps/django_app/views.py
social/apps/django_app/default/__init__.py
social/apps/django_app/default/admin.py
social/apps/django_app/default/config.py
social/apps/django_app/default/fields.py
social/apps/django_app/default/managers.py
social/apps/django_app/default/models.py
social/apps/django_app/default/tests.py
social/apps/django_app/default/migrations/0001_initial.py
social/apps/django_app/default/migrations/0002_add_related_name.py
social/apps/django_app/default/migrations/0003_alter_email_max_length.py
social/apps/django_app/default/migrations/0004_auto_20160423_0400.py
social/apps/django_app/default/migrations/0005_auto_20160727_2333.py
social/apps/django_app/default/migrations/__init__.py
social/apps/django_app/default/south_migrations/0001_initial.py
social/apps/django_app/default/south_migrations/__init__.py
social/apps/django_app/me/__init__.py
social/apps/django_app/me/config.py
social/apps/django_app/me/models.py
social/apps/django_app/me/tests.py
social/apps/flask_app/__init__.py
social/apps/flask_app/routes.py
social/apps/flask_app/template_filters.py
social/apps/flask_app/utils.py
social/apps/flask_app/default/__init__.py
social/apps/flask_app/default/models.py
social/apps/flask_app/me/__init__.py
social/apps/flask_app/me/models.py
social/apps/flask_app/peewee/__init__.py
social/apps/flask_app/peewee/models.py
social/apps/pyramid_app/__init__.py
social/apps/pyramid_app/models.py
social/apps/pyramid_app/utils.py
