Metadata-Version: 1.1
Name: mj-python-social-auth
Version: 0.2.22
Summary: Python social authentication made simple.
Home-page: https://github.com/Mojob/python-social-auth
Author: BS
Author-email: bs@mojob.io
License: BSD
Platform: UNKNOWN
Classifier: Development Status :: 4 - Beta
